{
    "話数": {
        "0": "第1話",
        "1": "第2話",
        "2": "第3話",
        "3": "第4話",
        "4": "第5話",
        "5": "第6話",
        "6": "第7話",
        "7": "第8話",
        "8": "第9話",
        "9": "第10話",
        "10": "第11話",
        "11": "第12話",
        "12": "第13話",
        "13": "第14話",
        "14": "第15話",
        "15": "第16話",
        "16": "第17話",
        "17": "第18話",
        "18": "第19話",
        "19": "第20話",
        "20": "第21話",
        "21": "第22話",
        "22": "第23話",
        "23": "第24話",
        "24": "第25話",
        "25": "第26話",
        "26": "第27話",
        "27": "第28話",
        "28": "第29話",
        "29": "第30話",
        "30": "第31話",
        "31": "第32話",
        "32": "第33話",
        "33": "第34話",
        "34": "第35話",
        "35": "第36話",
        "36": "第37話",
        "37": "第38話",
        "38": "第39話",
        "39": "第40話",
        "40": "第41話",
        "41": "第42話",
        "42": "第43話",
        "43": "第44話",
        "44": "第45話",
        "45": "第46話",
        "46": "第47話",
        "47": "第48話",
        "48": "第49話",
        "49": "第50話",
        "50": "第51話"
    },
    "サブタイトル": {
        "0": "スタア誕生!",
        "1": "りずむ、心のジャンプ!",
        "2": "これがコーチ!? ラビチとベアチ",
        "3": "イースターは胸キュン体験!",
        "4": "パパにはナイショでファッションショー",
        "5": "プリズムの輝きはいつもここに",
        "6": "絶交!? あいらとりずむの大ゲンカ",
        "7": "りずむピンチ! お勉強大作戦",
        "8": "学園祭と秘密の約束",
        "9": "雨のちラブリーレインボー",
        "10": "開幕! ティアラカップ",
        "11": "勝利の栄冠（ティアラ）は誰の手に!?",
        "12": "アンディの涙",
        "13": "みおんスイッチオン",
        "14": "めらめらハートがあつくなる!",
        "15": "ネコチの試練",
        "16": "ハピラキサマーはケーキで特訓!",
        "17": "夜空に花咲く恋ゴコロ",
        "18": "デュオ決定! 運命のガールズ・デート",
        "19": "ライバルは関西っ娘! セレナとかのん登場!!",
        "20": "嵐のサマークイーンカップ",
        "21": "スケート座の祝福を君に!",
        "22": "MARsドキドキ芸能界デビュー",
        "23": "修学旅行でお笑い対決",
        "24": "友情の誓い! オーロラの翼",
        "25": "こねてまとめる! 勝負のプリティーレシピ",
        "26": "南国ビーチのドルフィンビーナス",
        "27": "頑固オヤジにはちみつキッス",
        "28": "トリオでジャンプ! Hip Hop Win!",
        "29": "ドキドキハロウィンはときめきじゃナイト☆",
        "30": "あいらとふれあ、コラボっちゃお♥",
        "31": "爆笑! せれのん浅草漫才修行",
        "32": "あいら in ワンダーガール",
        "33": "これって恋!? 芸能界ラブバトル",
        "34": "MARsドリームライブ!",
        "35": "かなめは天使（エンジェル）? それとも悪魔（デビル）?",
        "36": "激闘! クリスタルハイヒールカップ",
        "37": "ミラクル・スノーの降る夜に",
        "38": "新春特番・プリズムショーの魅力に迫る!",
        "39": "それぞれの決意",
        "40": "ピュアプレミアムウェディングの願い",
        "41": "りずむとそなた、運命の再会",
        "42": "友情のピュアホワイトウェディング",
        "43": "スイート&ビターバレンタイン",
        "44": "光訪ねてブエノスアイレス",
        "45": "対決! あいらVSりずむ",
        "46": "ファイナリストをかけて",
        "47": "そなたの冬",
        "48": "舞い上がれ! オーロラの翼",
        "49": "新プリズムクイーン誕生!",
        "50": "Dream goes on…"
    },
    "脚本": {
        "0": "赤尾でこ",
        "1": "赤尾でこ",
        "2": "伊福部崇",
        "3": "坪田文",
        "4": "田口智子",
        "5": "井内秀治",
        "6": "村上桃子",
        "7": "伊福部崇",
        "8": "坪田文",
        "9": "田口智子",
        "10": "赤尾でこ",
        "11": "赤尾でこ",
        "12": "井内秀治",
        "13": "村上桃子",
        "14": "伊福部崇",
        "15": "田口智子",
        "16": "坪田文",
        "17": "村上桃子",
        "18": "伊福部崇",
        "19": "赤尾でこ",
        "20": "赤尾でこ",
        "21": "坪田文",
        "22": "田口智子",
        "23": "村上桃子",
        "24": "井内秀治",
        "25": "赤尾でこ",
        "26": "伊福部崇",
        "27": "坪田文",
        "28": "井内秀治",
        "29": "坪田文",
        "30": "田口智子",
        "31": "伊福部崇",
        "32": "赤尾でこ",
        "33": "村上桃子",
        "34": "坪田文",
        "35": "赤尾でこ",
        "36": "赤尾でこ",
        "37": "井内秀治",
        "38": "坪田文",
        "39": "伊福部崇",
        "40": "赤尾でこ",
        "41": "田口智子",
        "42": "村上桃子",
        "43": "赤尾でこ",
        "44": "坪田文",
        "45": "井内秀治",
        "46": "伊福部崇",
        "47": "坪田文",
        "48": "赤尾でこ",
        "49": "赤尾でこ",
        "50": "坪田文"
    },
    "絵コンテ": {
        "0": "青葉譲",
        "1": "青葉譲",
        "2": "藤原良二",
        "3": "殿勝秀樹",
        "4": "矢花馨",
        "5": "矢花馨",
        "6": "青葉譲",
        "7": "藤原良二",
        "8": "誌村宏明",
        "9": "近藤信宏",
        "10": "石踊宏",
        "11": "京極尚彦",
        "12": "京極尚彦",
        "13": "本田敬一 川島尚",
        "14": "藤原良二",
        "15": "近藤信宏",
        "16": "矢花馨",
        "17": "徳本善信",
        "18": "藤原良二",
        "19": "京極尚彦",
        "20": "青葉譲",
        "21": "矢花馨",
        "22": "近藤信宏",
        "23": "石踊宏",
        "24": "藤原良二",
        "25": "青葉譲",
        "26": "誌村宏明",
        "27": "藤原良二",
        "28": "藤原良二",
        "29": "京極尚彦",
        "30": "藤原良二",
        "31": "徳本善信",
        "32": "近藤信宏",
        "33": "矢花馨",
        "34": "藤原良二",
        "35": "青葉譲",
        "36": "青葉譲",
        "37": "青葉譲",
        "38": "徳本善信",
        "39": "青葉譲",
        "40": "矢花馨",
        "41": "藤原良二 青葉譲",
        "42": "誌村宏明",
        "43": "青葉譲",
        "44": "京極尚彦",
        "45": "井内秀治 青葉譲",
        "46": "藤原良二 青葉譲",
        "47": "矢花馨 青葉譲",
        "48": "青葉譲",
        "49": "青葉譲",
        "50": "京極尚彦"
    },
    "演出": {
        "0": "京極尚彦",
        "1": "徳本善信",
        "2": "関田修",
        "3": "関田修",
        "4": "関田修",
        "5": "岩田義彦",
        "6": "小林浩輔",
        "7": "徳本善信",
        "8": "加藤顕",
        "9": "矢花馨",
        "10": "関田修",
        "11": "関田修",
        "12": "関田修",
        "13": "徳本善信",
        "14": "江島泰男",
        "15": "岩田義彦",
        "16": "小林浩輔",
        "17": "小林浩輔",
        "18": "加藤顕",
        "19": "加藤顕",
        "20": "関田修",
        "21": "酒井和男",
        "22": "江島泰男",
        "23": "三好正人",
        "24": "徳本善信",
        "25": "徳本善信",
        "26": "関田修",
        "27": "根岸宏樹",
        "28": "徳本善信",
        "29": "徳本善信",
        "30": "加藤顕",
        "31": "加藤顕",
        "32": "関田修",
        "33": "関田修",
        "34": "小林浩輔",
        "35": "徳本善信",
        "36": "京極尚彦",
        "37": "根岸宏樹",
        "38": "根岸宏樹",
        "39": "徳本善信",
        "40": "三好正人",
        "41": "関田修",
        "42": "加藤顕",
        "43": "徳本善信",
        "44": "徳本善信",
        "45": "徳本善信",
        "46": "綿田慎也",
        "47": "関田修",
        "48": "加藤顕",
        "49": "徳本善信",
        "50": "徳本善信"
    },
    "作画監督": {
        "0": "池田有、稲吉朝子 空流辺広子、しんぼたくろう",
        "1": "森本由布希",
        "2": "窪敏、田中正之",
        "3": "空流辺広子",
        "4": "石井ゆみこ",
        "5": "加野晃",
        "6": "日高真由美、古池敏也",
        "7": "しんぼたくろう",
        "8": "池田有、村上やすひと 川島尚",
        "9": "森本由布希",
        "10": "空流辺広子",
        "11": "石井ゆみこ",
        "12": "竹知仁美",
        "13": "本田敬一",
        "14": "村上やすひと、空流辺広子",
        "15": "加野晃",
        "16": "日高真由美、古池敏也",
        "17": "しんぼたくろう",
        "18": "池田有、空流辺広子",
        "19": "石井ゆみこ、本多みゆき 星野玲香",
        "20": "空流辺広子",
        "21": "糸島雅彦",
        "22": "村上泰民、小林亮",
        "23": "森本由布希",
        "24": "柳瀬譲二、空流辺広子",
        "25": "川島尚",
        "26": "空流辺広子、工藤利春",
        "27": "玉利和枝",
        "28": "しんぼたくろう",
        "29": "石井ゆみ子",
        "30": "池田有",
        "31": "伊藤大翼、稲吉朝子 空流辺広子",
        "32": "空流辺広子",
        "33": "糸島雅彦",
        "34": "日高真由美、古池敏也",
        "35": "しんぼたくろう",
        "36": "ワタナベケンイチ、藤田明",
        "37": "玉利和枝",
        "38": "池田有",
        "39": "石井ゆみ子",
        "40": "森本由布希",
        "41": "空流辺広子",
        "42": "奥野浩行",
        "43": "しんぼたくろう",
        "44": "ワタナベケンイチ",
        "45": "川島尚、伊藤大翼 糸島雅彦、しんぼたくろう",
        "46": "Park Chan-Young、Cha Sang-Hoon 池田有",
        "47": "空流辺広子",
        "48": "石井ゆみ子",
        "49": "森本由布希",
        "50": "しんぼたくろう"
    },
    "放送日 (TXN)": {
        "0": "2011\/04\/09",
        "1": "2011\/04\/16",
        "2": "2011\/04\/23",
        "3": "2011\/04\/30",
        "4": "2011\/05\/07",
        "5": "2011\/05\/14",
        "6": "2011\/05\/21",
        "7": "2011\/05\/28",
        "8": "2011\/06\/04",
        "9": "2011\/06\/11",
        "10": "2011\/06\/18",
        "11": "2011\/06\/25",
        "12": "2011\/07\/02",
        "13": "2011\/07\/09",
        "14": "2011\/07\/16",
        "15": "2011\/07\/23",
        "16": "2011\/07\/30",
        "17": "2011\/08\/06",
        "18": "2011\/08\/13",
        "19": "2011\/08\/20",
        "20": "2011\/08\/27",
        "21": "2011\/09\/03",
        "22": "2011\/09\/10",
        "23": "2011\/09\/17",
        "24": "2011\/09\/24",
        "25": "2011\/10\/01",
        "26": "2011\/10\/08",
        "27": "2011\/10\/15",
        "28": "2011\/10\/22",
        "29": "2011\/10\/29",
        "30": "2011\/11\/05",
        "31": "2011\/11\/12",
        "32": "2011\/11\/19",
        "33": "2011\/11\/26",
        "34": "2011\/12\/03",
        "35": "2011\/12\/10",
        "36": "2011\/12\/17",
        "37": "2011\/12\/24",
        "38": "2012\/01\/07",
        "39": "2012\/01\/14",
        "40": "2012\/01\/21",
        "41": "2012\/01\/28",
        "42": "2012\/02\/04",
        "43": "2012\/02\/11",
        "44": "2012\/02\/18",
        "45": "2012\/02\/25",
        "46": "2012\/03\/03",
        "47": "2012\/03\/10",
        "48": "2012\/03\/17",
        "49": "2012\/03\/24",
        "50": "2012\/03\/31"
    }
}